LICENSE.txt
MANIFEST.in
Makefile
README.md
pyproject.toml
requirements.txt
setup.cfg
setup.py
mrrt/__init__.py
mrrt.operators.egg-info/PKG-INFO
mrrt.operators.egg-info/SOURCES.txt
mrrt.operators.egg-info/dependency_links.txt
mrrt.operators.egg-info/requires.txt
mrrt.operators.egg-info/top_level.txt
mrrt/operators/LinOp.py
mrrt/operators/_DCT.py
mrrt/operators/_DWT.py
mrrt/operators/_FFT.py
mrrt/operators/_FiniteDifference.py
mrrt/operators/_OrthoMatrix.py
mrrt/operators/_TV.py
mrrt/operators/__init__.py
mrrt/operators/_block_transforms.py
mrrt/operators/_cycle_spinning.py
mrrt/operators/mixins.py
mrrt/operators/version.py
mrrt/operators/linop/README.rst
mrrt/operators/linop/__init__.py
mrrt/operators/linop/_types.py
mrrt/operators/linop/blkop.py
mrrt/operators/linop/linop.py
mrrt/operators/linop/setup.py
mrrt/operators/linop/tests/test_blkop.py
mrrt/operators/linop/tests/test_linop.py
mrrt/operators/tests/__init__.py
mrrt/operators/tests/test_array_linop.py
mrrt/operators/tests/test_basic_linops.py
mrrt/operators/tests/test_block.py
mrrt/operators/tests/test_composite.py
mrrt/operators/tests/test_dct.py
mrrt/operators/tests/test_dwt.py
mrrt/operators/tests/test_fft.py
mrrt/operators/tests/test_finite_difference.py
mrrt/operators/tests/test_ortho_matrix.py
mrrt/operators/tests/test_tv.py