Metadata-Version: 1.2
Name: mrrt.operators
Version: 0.2.1
Summary: Linear Operators for Image Reconstruction
Home-page: http://github.com/mritools/mrrt.operators
Author: Gregory R. Lee
Author-email: grlee77@gmail.com
Maintainer: Gregory R. Lee
Maintainer-email: grlee77@gmail.com
License: BSD
Platform: OS Independent
Classifier: Development Status :: 4 - Beta
Classifier: Environment :: Console
Classifier: Intended Audience :: Science/Research
Classifier: License :: OSI Approved :: BSD License
Classifier: Operating System :: OS Independent
Classifier: Programming Language :: Python
Classifier: Programming Language :: Python :: 3
Classifier: Programming Language :: Python :: 3.6
Classifier: Programming Language :: Python :: 3.7
Classifier: Programming Language :: Python :: 3.8
Classifier: Programming Language :: Python :: 3 :: Only
Classifier: Programming Language :: Python :: Implementation :: CPython
Classifier: Topic :: Scientific/Engineering
Requires: numpy
Requires: mrrt.utils
Requires-Python: >= 3.6
